EXP-7/DFF.v
module DFF (
    input D,clk,
    output Q, Qb
);
    reg Q,Qb;
    always @(posedge clk) begin
        case (D)
            1'b0: Q=1'b0;
            1'b1: Q=1'b1;
            default: Q = 1'b0;
        endcase
        Qb=~Q;
    end   
endmodule

EXP-7/FSM.v
module FSM (
    input x,clk,
    output [3:0] Q,
    output y

);
wire D2,D1,D0,Qb2,Qb1,Qb0,y;
assign D2 = (Q[1] && Q[0]) || (Q[2] && Qb0);
assign D1 = (Q[1] && Qb0) || (Qb2 && Qb1 && Q[0]);
assign D0 = (Qb0 && (Q[2] || Q[1] || x));
assign y = (Q[1] && Q[0]) || (Q[2] && Q[0])  || (Qb2 && Qb1 && Qb0 && x);

DFF ff2(.D(D2), .clk(clk), .Q(Q[2]), .Qb(Qb2));
DFF ff1(.D(D1), .clk(clk), .Q(Q[1]), .Qb(Qb1));
DFF ff0(.D(D0), .clk(clk), .Q(Q[0]), .Qb(Qb0));
    
endmodule

EXP-7/FSM_tb.v
module FSM_tb;
    reg clk, x;
    wire y;

    initial #500 $finish;
    FSM M_UUT(.clk(clk), .x(x), .y(y));
    initial begin
        $dumpfile("FSM.vcd");
        $dumpvars(0,FSM_tb);
        clk = 0;
        forever begin
            #10 clk = ~clk;
        end
    end

    initial begin
        x=1;
    end

    
endmodule

EXP-7/FSM.vcd
$date
	Tue May 18 10:22:57 2021
$end
$version
	Icarus Verilog
$end
$timescale
	1s
$end
$scope module FSM_tb $end
$var wire 1 ! y $end
$var reg 1 " clk $end
$var reg 1 # x $end
$scope module M_UUT $end
$var wire 1 $ D0 $end
$var wire 1 % D1 $end
$var wire 1 & D2 $end
$var wire 1 " clk $end
$var wire 1 # x $end
$var wire 1 ! y $end
$var wire 1 ' Qb2 $end
$var wire 1 ( Qb1 $end
$var wire 1 ) Qb0 $end
$var wire 4 * Q [3:0] $end
$scope module ff0 $end
$var wire 1 $ D $end
$var wire 1 " clk $end
$var reg 1 + Q $end
$var reg 1 ) Qb $end
$upscope $end
$scope module ff1 $end
$var wire 1 % D $end
$var wire 1 " clk $end
$var reg 1 , Q $end
$var reg 1 ( Qb $end
$upscope $end
$scope module ff2 $end
$var wire 1 & D $end
$var wire 1 " clk $end
$var reg 1 - Q $end
$var reg 1 ' Qb $end
$upscope $end
$upscope $end
$upscope $end
$enddefinitions $end
#0
$dumpvars
x-
x,
x+
bzxxx *
x)
x(
x'
x&
x%
x$
1#
0"
x!
$end
#10
1!
0%
0&
1$
1'
0-
1(
0,
1)
bz000 *
0+
1"
#20
0"
#30
0!
1%
0$
0)
bz001 *
1+
1"
#40
0"
#50
0!
1$
0(
1,
1)
bz010 *
0+
1"
#60
0"
#70
1!
1&
0%
0$
0)
bz011 *
1+
1"
#80
0"
#90
0!
0%
1$
0'
1-
1(
0,
1)
bz100 *
0+
1"
#100
0"
#110
1!
0&
0$
0)
bz101 *
1+
1"
#120
0"
#130
0&
1$
1'
0-
1)
bz000 *
0+
1"
#140
0"
#150
0!
1%
0$
0)
bz001 *
1+
1"
#160
0"
#170
0!
1$
0(
1,
1)
bz010 *
0+
1"
#180
0"
#190
1!
1&
0%
0$
0)
bz011 *
1+
1"
#200
0"
#210
0!
0%
1$
0'
1-
1(
0,
1)
bz100 *
0+
1"
#220
0"
#230
1!
0&
0$
0)
bz101 *
1+
1"
#240
0"
#250
0&
1$
1'
0-
1)
bz000 *
0+
1"
#260
0"
#270
0!
1%
0$
0)
bz001 *
1+
1"
#280
0"
#290
0!
1$
0(
1,
1)
bz010 *
0+
1"
#300
0"
#310
1!
1&
0%
0$
0)
bz011 *
1+
1"
#320
0"
#330
0!
0%
1$
0'
1-
1(
0,
1)
bz100 *
0+
1"
#340
0"
#350
1!
0&
0$
0)
bz101 *
1+
1"
#360
0"
#370
0&
1$
1'
0-
1)
bz000 *
0+
1"
#380
0"
#390
0!
1%
0$
0)
bz001 *
1+
1"
#400
0"
#410
0!
1$
0(
1,
1)
bz010 *
0+
1"
#420
0"
#430
1!
1&
0%
0$
0)
bz011 *
1+
1"
#440
0"
#450
0!
0%
1$
0'
1-
1(
0,
1)
bz100 *
0+
1"
#460
0"
#470
1!
0&
0$
0)
bz101 *
1+
1"
#480
0"
#490
0&
1$
1'
0-
1)
bz000 *
0+
1"
