EXP-6/Gray Code Counter/SR_FF.v
module SR_FF (
    input [1:0] sr,
    input clk,
    output Q,Qb
);
    reg Q,Qb;
    always @(posedge clk) begin
        case (sr)
            2'b00: Q=Q;
            2'b01: Q=1'b0;
            2'b10: Q=1'b1;
            2'b11: Q=1'bz;
            default: Q=1'b0;
        endcase
        Qb=~Q;
    end

   
endmodule

EXP-6/Gray Code Counter/gray_code_counter.v
module gray_code_counter (
    input clk,
    output [3:0] Q
);
    wire S3,S2,S1,S0,R3,R2,R1,R0,Qb3,Qb2,Qb1,Qb0;
    assign S3 = (Q[2] && Qb1 && Qb0);
    assign R3 = (Qb2 && Qb1 && Qb0);
    assign S2 = (Qb3 && Q[1] && Qb0);
    assign R2 = (Q[3] && Q[1] && Qb0);
    assign S1 = (Qb3 && Qb2 && Q[0]) || (Q[3] && Q[2] && Q[0]);
    assign R1 = (Qb3 && Q[2] && Q[0]) || (Q[3] && Qb2 && Q[0]);
    assign S0 = (Qb3 && Qb2 && Qb1) || (Qb3 && Q[2] && Q[1]) || (Q[3] && Qb2 && Q[1]) || (Q[3] && Q[2] && Qb1);
    assign R0 = (Qb3 && Qb2 && Q[1]) || (Qb3 && Q[2] && Qb1) || (Q[3] && Qb2 && Qb1) || (Q[3] && Q[2] && Q[1]);

    SR_FF ff3(.clk(clk), .sr({S3,R3}), .Q(Q[3]), .Qb(Qb3));
    SR_FF ff2(.clk(clk), .sr({S2,R2}), .Q(Q[2]), .Qb(Qb2));
    SR_FF ff1(.clk(clk), .sr({S1,R1}), .Q(Q[1]), .Qb(Qb1));
    SR_FF ff0(.clk(clk), .sr({S0,R0}), .Q(Q[0]), .Qb(Qb0));

    
endmodule

EXP-6/Gray Code Counter/gray_code_counter_tb.v
module gray_code_counter_tb;

    wire [3:0] Q;
    reg clk;

    gray_code_counter M_UUT(.clk(clk), .Q(Q));
    
    initial #500 $finish;
    initial begin
        $dumpfile("grayCode.vcd");
        $dumpvars(0,gray_code_counter_tb); 
        clk = 0;
        forever begin
            #10 clk = ~clk;
        end
    end
    
endmodule

EXP-6/Gray Code Counter/grayCode.vcd
$date
	Mon May 17 19:49:58 2021
$end
$version
	Icarus Verilog
$end
$timescale
	1s
$end
$scope module gray_code_counter_tb $end
$var wire 4 ! Q [3:0] $end
$var reg 1 " clk $end
$scope module M_UUT $end
$var wire 1 # R0 $end
$var wire 1 $ R1 $end
$var wire 1 % R2 $end
$var wire 1 & R3 $end
$var wire 1 ' S0 $end
$var wire 1 ( S1 $end
$var wire 1 ) S2 $end
$var wire 1 * S3 $end
$var wire 1 " clk $end
$var wire 1 + Qb3 $end
$var wire 1 , Qb2 $end
$var wire 1 - Qb1 $end
$var wire 1 . Qb0 $end
$var wire 4 / Q [3:0] $end
$scope module ff0 $end
$var wire 1 " clk $end
$var wire 2 0 sr [1:0] $end
$var reg 1 1 Q $end
$var reg 1 . Qb $end
$upscope $end
$scope module ff1 $end
$var wire 1 " clk $end
$var wire 2 2 sr [1:0] $end
$var reg 1 3 Q $end
$var reg 1 - Qb $end
$upscope $end
$scope module ff2 $end
$var wire 1 " clk $end
$var wire 2 4 sr [1:0] $end
$var reg 1 5 Q $end
$var reg 1 , Qb $end
$upscope $end
$scope module ff3 $end
$var wire 1 " clk $end
$var wire 2 6 sr [1:0] $end
$var reg 1 7 Q $end
$var reg 1 + Qb $end
$upscope $end
$upscope $end
$upscope $end
$enddefinitions $end
#0
$dumpvars
x7
bx 6
x5
bx 4
x3
bx 2
x1
bx 0
bx /
x.
x-
x,
x+
x*
x)
x(
x'
x&
x%
x$
x#
0"
bx !
$end
#10
0#
b10 0
1'
0*
0%
0$
b0 2
0(
b0 4
0)
b1 6
1&
1+
07
1,
05
1-
03
1.
b0 !
b0 /
01
1"
#20
0"
#30
b10 2
1(
b0 6
0&
0.
b1 !
b1 /
11
1"
#40
0"
#50
1#
b1 0
0'
0-
b11 !
b11 /
13
1"
#60
0"
#70
b0 2
0(
b10 4
1)
1.
b10 !
b10 /
01
1"
#80
0"
#90
1'
b10 0
0#
0,
b110 !
b110 /
15
1"
#100
0"
#110
b1 2
1$
b0 4
0)
0.
b111 !
b111 /
11
1"
#120
0"
#130
0'
b1 0
1#
1-
b101 !
b101 /
03
1"
#140
0"
#150
b0 2
0$
b10 6
1*
1.
b100 !
b100 /
01
1"
#160
0"
#170
0#
b10 0
1'
0+
b1100 !
b1100 /
17
1"
#180
0"
#190
b10 2
1(
b0 6
0*
0.
b1101 !
b1101 /
11
1"
#200
0"
#210
1#
b1 0
0'
0-
b1111 !
b1111 /
13
1"
#220
0"
#230
b0 2
0(
b1 4
1%
1.
b1110 !
b1110 /
01
1"
#240
0"
#250
1'
b10 0
0#
1,
b1010 !
b1010 /
05
1"
#260
0"
#270
b1 2
1$
b0 4
0%
0.
b1011 !
b1011 /
11
1"
#280
0"
#290
0'
b1 0
1#
1-
b1001 !
b1001 /
03
1"
#300
0"
#310
b0 2
0$
b1 6
1&
1.
b1000 !
b1000 /
01
1"
#320
0"
#330
1'
b10 0
0#
1+
b0 !
b0 /
07
1"
#340
0"
#350
b10 2
1(
b0 6
0&
0.
b1 !
b1 /
11
1"
#360
0"
#370
1#
b1 0
0'
0-
b11 !
b11 /
13
1"
#380
0"
#390
b0 2
0(
b10 4
1)
1.
b10 !
b10 /
01
1"
#400
0"
#410
1'
b10 0
0#
0,
b110 !
b110 /
15
1"
#420
0"
#430
b1 2
1$
b0 4
0)
0.
b111 !
b111 /
11
1"
#440
0"
#450
0'
b1 0
1#
1-
b101 !
b101 /
03
1"
#460
0"
#470
b0 2
0$
b10 6
1*
1.
b100 !
b100 /
01
1"
#480
0"
#490
0#
b10 0
1'
0+
b1100 !
b1100 /
17
1"
