EXP-6/Synchronous Ring Counter/DFF.V
module DFF1 (
    input D,clk,
    output Q, Qb
);
    initial begin
        Q = 1'b1;
        Qb = 1'b0;
    end
    reg Q, Qb;
    always @(posedge clk) begin
        Q=D;
        Qb=~Q;
    end   
endmodule

EXP-6/Synchronous Ring Counter/DFF2.v
module DFF2 (
    input D,clk,
    output Q, Qb
);
    initial begin
        Q = 1'b0;
        Qb = 1'b1;
    end
    reg Q, Qb;
    always @(posedge clk) begin
        Q=D;
        Qb=~Q;
    end   
endmodule

EXP-6/Synchronous Ring Counter/sync_ring_counter.v
module sync_ring_counter (
    input clk,
    output [3:0] Q
);
    

    wire D3,D2,D1,D0,Qb3,Qb2,Qb1,Qb0;
    assign D3 = (Qb1 && Q[0]) || (Q[1] && Qb0);
    assign D2 = Q[3];
    assign D1 = Q[2];
    assign D0 = Q[1];  
    

    DFF2 ff3(.clk(clk), .D(D3), .Q(Q[3]), .Qb(Qb3));
    DFF1 ff2(.clk(clk), .D(D2), .Q(Q[2]), .Qb(Qb2));
    DFF2 ff1(.clk(clk), .D(D1), .Q(Q[1]), .Qb(Qb1));
    DFF1 ff0(.clk(clk), .D(D0), .Q(Q[0]), .Qb(Qb0));
    
endmodule

EXP-6/Synchronous Ring Counter/sync_ring_counter_tb.v
module sync_ring_counter_tb;
    
    wire [3:0] Q;
    reg clk;

    sync_ring_counter M_UUT(.clk(clk), .Q(Q));
    
    initial #500 $finish;
    initial begin
        $dumpfile("syncRing.vcd");
        $dumpvars(0,sync_ring_counter_tb);
        clk = 0;
        forever begin
            #10 clk = ~clk;
        end
    end

endmodule

EXP-6/Synchronous Ring Counter/syncRing.vcd
$date
	Tue May 18 15:15:53 2021
$end
$version
	Icarus Verilog
$end
$timescale
	1s
$end
$scope module sync_ring_counter_tb $end
$var wire 4 ! Q [3:0] $end
$var reg 1 " clk $end
$scope module M_UUT $end
$var wire 1 # D3 $end
$var wire 1 " clk $end
$var wire 1 $ Qb3 $end
$var wire 1 % Qb2 $end
$var wire 1 & Qb1 $end
$var wire 1 ' Qb0 $end
$var wire 4 ( Q [3:0] $end
$var wire 1 ) D2 $end
$var wire 1 * D1 $end
$var wire 1 + D0 $end
$scope module ff0 $end
$var wire 1 + D $end
$var wire 1 " clk $end
$var reg 1 , Q $end
$var reg 1 ' Qb $end
$upscope $end
$scope module ff1 $end
$var wire 1 * D $end
$var wire 1 " clk $end
$var reg 1 - Q $end
$var reg 1 & Qb $end
$upscope $end
$scope module ff2 $end
$var wire 1 ) D $end
$var wire 1 " clk $end
$var reg 1 . Q $end
$var reg 1 % Qb $end
$upscope $end
$scope module ff3 $end
$var wire 1 # D $end
$var wire 1 " clk $end
$var reg 1 / Q $end
$var reg 1 $ Qb $end
$upscope $end
$upscope $end
$upscope $end
$enddefinitions $end
#0
$dumpvars
0/
1.
0-
1,
0+
1*
0)
b101 (
0'
1&
0%
1$
1#
0"
b101 !
$end
#10
1)
0*
1+
0$
1/
1%
0.
0&
1-
1'
b1010 !
b1010 (
0,
1"
#20
0"
#30
0+
1*
0'
1,
1&
0-
0%
b1101 !
b1101 (
1.
1"
#40
0"
#50
1+
0&
1-
1'
b1110 !
b1110 (
0,
1"
#60
0"
#70
0#
0'
b1111 !
b1111 (
1,
1"
#80
0"
#90
0)
1$
b111 !
b111 (
0/
1"
#100
0"
#110
0*
1%
b11 !
b11 (
0.
1"
#120
0"
#130
1#
0+
1&
b1 !
b1 (
0-
1"
#140
0"
#150
0#
1)
1'
0,
0$
b1000 !
b1000 (
1/
1"
#160
0"
#170
0)
1*
1$
0/
0%
b100 !
b100 (
1.
1"
#180
0"
#190
1#
1+
0*
0&
1-
1%
b10 !
b10 (
0.
1"
#200
0"
#210
1)
0+
0$
1/
1&
0-
0'
b1001 !
b1001 (
1,
1"
#220
0"
#230
0#
1*
1'
0,
0%
b1100 !
b1100 (
1.
1"
#240
0"
#250
1#
0)
1+
1$
0/
0&
b110 !
b110 (
1-
1"
#260
0"
#270
0#
0*
1)
0'
1,
1%
0.
0$
b1011 !
b1011 (
1/
1"
#280
0"
#290
1#
0)
1*
0+
1$
0/
0%
1.
1&
b101 !
b101 (
0-
1"
#300
0"
#310
1+
0*
1)
1'
0,
0&
1-
1%
0.
0$
b1010 !
b1010 (
1/
1"
#320
0"
#330
1*
0+
0%
1.
1&
0-
0'
b1101 !
b1101 (
1,
1"
#340
0"
#350
1+
1'
0,
0&
b1110 !
b1110 (
1-
1"
#360
0"
#370
0#
0'
b1111 !
b1111 (
1,
1"
#380
0"
#390
0)
1$
b111 !
b111 (
0/
1"
#400
0"
#410
0*
1%
b11 !
b11 (
0.
1"
#420
0"
#430
1#
0+
1&
b1 !
b1 (
0-
1"
#440
0"
#450
0#
1)
0$
1/
1'
b1000 !
b1000 (
0,
1"
#460
0"
#470
1*
0)
0%
1.
1$
b100 !
b100 (
0/
1"
#480
0"
#490
1#
0*
1+
1%
0.
0&
b10 !
b10 (
1-
1"
